[
  {
    "id": 1,
    "text": ">>> Połączenie z bazą archiwalną: ustanowione.",
    "delay": 500,
    "duration": 1500
  },
  {
    "id": 2,
    "text": ">>> Analiza dostępnych modułów informacyjnych...",
    "delay": 1000,
    "duration": 1500
  },
  {
    "id": 3,
    "text": ">>> Zlokalizowano 3 aktywne sektory danych:",
    "delay": 1000,
    "duration": 1500
  },
  {
    "id": 4,
    "text": "[1] Historia świata po Upadku",
    "delay": 1000,
    "duration": 1000,
    "type": "system_message"
  },
  {
    "id": 5,
    "text": "[2] Mapa sektorów głębi",
    "delay": 1000,
    "duration": 1000,
    "type": "system_message"
  },
  {
    "id": 6,
    "text": "[3] Zapiski świadomości AEL_09",
    "delay": 1000,
    "duration": 1000,
    "type": "system_message"
  },
  {
    "id": 7,
    "text": ">>> Ostrzeżenie: niektóre dane mogą wpłynąć na stabilność poznawczą.",
    "delay": 1500,
    "duration": 2000
  },
  {
    "id": 8,
    "text": ">>> Do którego sektora chcesz uzyskać dostęp.",
    "delay": 1000,
    "duration": 1000
  },
  {
    "id": 9,
    "text": "'history', 'map', 'AEL_09'",
    "delay": 1000,
    "duration": 1000,
    "type": "command"
  }
]
